{
    "timestamp": "2026-01-28T02:00:00+08:00",
    "philosophical_alignment": {
        "tone": "Discovery First applied with focus on metabolic debt and biological firewalls.",
        "methodology": "Triton baseline maintained, specifically parameter matching and aerosol isolation.",
        "safety_posture": "Conservative, stability-focused. Passed 5-subdomain Triton Anchor check."
    },
    "project_state": {
        "current_domain": "11_acclimation_quarantine",
        "current_subdomain": "invert_quarantine",
        "current_phase": "GENERATE",
        "completion_percentage": "34.3%"
    },
    "accumulated_learnings": [
        "Formalized the 'Shipping Triangle' (Oxygen, Temp, Waste) for logistics.",
        "Integrated the 'pH/Ammonia Rebound' effect as a critical safety warning.",
        "Established 'Aerosol Isolation' distancing vs. physical barriers mitigation.",
        "Linked 'Metabolic Debt' to the rate of acclimation recovery."
    ],
    "hidden_constraints": [
        "Navigation must account for on-the-fly subdomain insertions (e.g. coral_acclimation).",
        "Transfer rinse water disposal is a non-negotiable safety step."
    ],
    "advice_to_successor": "Domain 11 is progressing well. Moving to 'invert_quarantine'. Ensure the distinction between fish-safe and invert-safe medications is absolute. Focus on the biological reasoning: invertebrates like snails and shrimp are highly sensitive to rapid salinity changes and trace heavy metals."
}